{"models":{"Campaign":{"id":"kjzl6hvfrbw6c6l0qqf86u72cpx798lvf9yl71287gyeefvwc5lgb1nbqfmwms4","accountRelation":"list"}},"objects":{"CampaignLink":{"url":{"type":"string","required":true},"format":{"type":"reference","refType":"enum","refName":"CampaignMediaFormat","required":false}},"CampaignLiked":{"name":{"type":"string","required":false},"campaign":{"type":"id","required":false}},"CampaignPerkList":{"type":{"type":"string","required":false},"value":{"type":"string","required":false}},"Campaign":{"uid":{"type":"string","required":true},"goal":{"type":"integer","required":true},"name":{"type":"string","required":true},"image":{"type":"list","required":false,"item":{"type":"reference","refType":"object","refName":"CampaignLink","required":false}},"likes":{"type":"list","required":false,"item":{"type":"reference","refType":"object","refName":"CampaignLiked","required":false}},"perks":{"type":"list","required":false,"item":{"type":"reference","refType":"object","refName":"CampaignPerkList","required":false}},"video":{"type":"list","required":false,"item":{"type":"reference","refType":"object","refName":"CampaignLink","required":false}},"active":{"type":"boolean","required":true},"description":{"type":"string","required":true},"author":{"type":"view","viewType":"documentAccount"}}},"enums":{"CampaignMediaFormat":["IMAGE","VIDEO"]},"accountData":{"campaignList":{"type":"connection","name":"Campaign"}}}
